README.md
flask_run.py
setup.py
Flask_Run.egg-info/PKG-INFO
Flask_Run.egg-info/SOURCES.txt
Flask_Run.egg-info/dependency_links.txt
Flask_Run.egg-info/namespace_packages.txt
Flask_Run.egg-info/top_level.txt
Flask_Run.egg-info/zip-safe