Metadata-Version: 1.1
Name: Flask-Run
Version: 0.1.3
Summary: Flask-based web application runner
Home-page: https://github.com/salsita/flask-run
Author: Salsita Software
Author-email: python@salsitasoft.com
License: MIT
Download-URL: https://github.com/salsita/flask-run/tarball/v0.1.3
Keywords: flask
Platform: any
Classifier: Development Status :: 4 - Beta
Classifier: Environment :: Web Environment
Classifier: Framework :: Flask
Classifier: Operating System :: OS Independent
Classifier: Intended Audience :: Developers
Classifier: Programming Language :: Python
Classifier: Programming Language :: Python :: 2.7
Classifier: Programming Language :: Python :: 3.3
Classifier: Programming Language :: Python :: 3.4
Classifier: License :: OSI Approved :: MIT License
Classifier: Topic :: Internet :: WWW/HTTP :: Dynamic Content
Classifier: Topic :: Software Development :: Libraries :: Python Modules
